README
setup.cfg
setup.py
nuage/__init__.py
nuage/cli.py
nuage/client.py
nuage/plugin.py
nuage.egg-info/PKG-INFO
nuage.egg-info/SOURCES.txt
nuage.egg-info/dependency_links.txt
nuage.egg-info/entry_points.txt
nuage.egg-info/requires.txt
nuage.egg-info/top_level.txt
nuage/commands/__init__.py
nuage/commands/config.py
nuage/commands/console.py
nuage/commands/create.py
nuage/commands/domains.py
nuage/commands/list.py
nuage/commands/logs.py
nuage/commands/open.py
nuage/commands/rename.py
nuage/commands/sharing.py
nuage/commands/ssl.py
nuage/plugins/__init__.py
nuage/tests/__init__.py
nuage/tests/test_nuage_client.py