Metadata-Version: 1.0
Name: nuage
Version: 0.5
Summary: Command line client for manage applications in nuage platform
Home-page: http://www.nuagehq.com/
Author: The Nuage Team
Author-email: team@nuagehq.com
License: BSD
Keywords: cloud django wsgi deployment
Platform: UNKNOWN
Classifier: Development Status :: 3 - Alpha
Classifier: License :: OSI Approved :: BSD License
